cli.py
excel.py
functions.py
operations.py
asteq_treso-0.1.1.dist-info/LICENSE
asteq_treso-0.1.1.dist-info/METADATA
asteq_treso-0.1.1.dist-info/WHEEL
asteq_treso-0.1.1.dist-info/entry_points.txt
asteq_treso-0.1.1.dist-info/top_level.txt
asteq_treso-0.1.1.dist-info/RECORD
